odoo/addons/sale_coupon_commercial_partner_applicability/README.rst
odoo/addons/sale_coupon_commercial_partner_applicability/__init__.py
odoo/addons/sale_coupon_commercial_partner_applicability/__manifest__.py
odoo/addons/sale_coupon_commercial_partner_applicability/i18n/sale_coupon_commercial_partner_applicability.pot
odoo/addons/sale_coupon_commercial_partner_applicability/models/__init__.py
odoo/addons/sale_coupon_commercial_partner_applicability/models/coupon_coupon.py
odoo/addons/sale_coupon_commercial_partner_applicability/readme/CONTRIBUTORS.rst
odoo/addons/sale_coupon_commercial_partner_applicability/readme/DESCRIPTION.rst
odoo/addons/sale_coupon_commercial_partner_applicability/static/description/icon.png
odoo/addons/sale_coupon_commercial_partner_applicability/static/description/index.html
odoo/addons/sale_coupon_commercial_partner_applicability/tests/__init__.py
odoo/addons/sale_coupon_commercial_partner_applicability/tests/test_sale_coupon_apply_commercial_partner.py
odoo13_addon_sale_coupon_commercial_partner_applicability-13.0.1.0.1.dev3.dist-info/METADATA
odoo13_addon_sale_coupon_commercial_partner_applicability-13.0.1.0.1.dev3.dist-info/WHEEL
odoo13_addon_sale_coupon_commercial_partner_applicability-13.0.1.0.1.dev3.dist-info/top_level.txt
odoo13_addon_sale_coupon_commercial_partner_applicability-13.0.1.0.1.dev3.dist-info/RECORD
